{"note":"This file is an internal implementation detail to speed up HTML report generation. Its format can change at any time. You might be looking for the JSON report: https://coverage.rtfd.io/cmd.html#cmd-json","format":5,"version":"7.13.5","globals":"8684df4dd8d2e508b534199ee30aeba2","files":{"z_145eef247bfb46b6___init___py":{"hash":"fb63bd22ecf1b1b50f03256ab1f6b347","index":{"url":"z_145eef247bfb46b6___init___py.html","file":"src/__init__.py","description":"","nums":{"precision":0,"n_files":1,"n_statements":3,"n_excluded":0,"n_missing":0,"n_branches":0,"n_partial_branches":0,"n_missing_branches":0}}},"z_145eef247bfb46b6_decorators_py":{"hash":"8ee3fea125b98742373b6516cdcd376b","index":{"url":"z_145eef247bfb46b6_decorators_py.html","file":"src/decorators.py","description":"","nums":{"precision":0,"n_files":1,"n_statements":26,"n_excluded":0,"n_missing":0,"n_branches":2,"n_partial_branches":0,"n_missing_branches":0}}},"z_145eef247bfb46b6_external_api_py":{"hash":"bbd38dc1bb9674b67972287a6b1cc736","index":{"url":"z_145eef247bfb46b6_external_api_py.html","file":"src/external_api.py","description":"","nums":{"precision":0,"n_files":1,"n_statements":21,"n_excluded":0,"n_missing":0,"n_branches":4,"n_partial_branches":0,"n_missing_branches":0}}},"z_145eef247bfb46b6_generators_py":{"hash":"ec10070bc6b27bbe67e7e89884f0e573","index":{"url":"z_145eef247bfb46b6_generators_py.html","file":"src/generators.py","description":"","nums":{"precision":0,"n_files":1,"n_statements":16,"n_excluded":0,"n_missing":0,"n_branches":8,"n_partial_branches":0,"n_missing_branches":0}}},"z_145eef247bfb46b6_masks_py":{"hash":"73054b281b73083870cf378fa37bea62","index":{"url":"z_145eef247bfb46b6_masks_py.html","file":"src/masks.py","description":"","nums":{"precision":0,"n_files":1,"n_statements":11,"n_excluded":0,"n_missing":0,"n_branches":4,"n_partial_branches":0,"n_missing_branches":0}}},"z_145eef247bfb46b6_processing_py":{"hash":"aa69688f4ff3324049c78c3e98696a15","index":{"url":"z_145eef247bfb46b6_processing_py.html","file":"src/processing.py","description":"","nums":{"precision":0,"n_files":1,"n_statements":11,"n_excluded":0,"n_missing":0,"n_branches":0,"n_partial_branches":0,"n_missing_branches":0}}},"z_145eef247bfb46b6_utils_py":{"hash":"51254aa16ff27498542717e9d2cf33c1","index":{"url":"z_145eef247bfb46b6_utils_py.html","file":"src/utils.py","description":"","nums":{"precision":0,"n_files":1,"n_statements":13,"n_excluded":0,"n_missing":0,"n_branches":2,"n_partial_branches":0,"n_missing_branches":0}}},"z_145eef247bfb46b6_widget_py":{"hash":"d22bf44792f8b3606fcb2688c7ac8ab1","index":{"url":"z_145eef247bfb46b6_widget_py.html","file":"src/widget.py","description":"","nums":{"precision":0,"n_files":1,"n_statements":14,"n_excluded":0,"n_missing":0,"n_branches":4,"n_partial_branches":0,"n_missing_branches":0}}}}}